[{"time_in_ms": "500", "costs": 714.0, "plan_selection": "n/a"}, {"time_in_ms": "1000", "costs": 519.0, "plan_selection": "n/a"}, {"time_in_ms": "1500", "costs": 441.0, "plan_selection": "n/a"}, {"time_in_ms": "9500", "costs": 433.0, "plan_selection": "n/a"}, {"time_in_ms": "10000", "costs": 424.0, "plan_selection": "n/a"}, {"time_in_ms": "14500", "costs": 395.0, "plan_selection": "n/a"}, {"time_in_ms": "20500", "costs": 346.0, "plan_selection": [13, 34, 89, 113, 125, 170, 196, 234, 246, 291, 301, 357, 370, 399, 424, 475, 488, 514, 548, 576, 621, 653, 671, 705, 746, 778, 796, 825, 844, 895]}]