[{"time_in_ms": "500", "costs": 628.0, "plan_selection": "n/a"}, {"time_in_ms": "1000", "costs": 532.0, "plan_selection": "n/a"}, {"time_in_ms": "1500", "costs": 417.0, "plan_selection": "n/a"}, {"time_in_ms": "2000", "costs": 353.0, "plan_selection": "n/a"}, {"time_in_ms": "2500", "costs": 268.0, "plan_selection": "n/a"}, {"time_in_ms": "3000", "costs": 208.0, "plan_selection": [20, 122, 183, 270, 318, 394, 448, 518, 605, 662, 735, 823, 852, 921, 981, 1088, 1189, 1214, 1308, 1375, 1419, 1504, 1575, 1665, 1731, 1813, 1834, 1903, 2011, 2035]}]