[{"time_in_ms": "500", "costs": 662.0, "plan_selection": "n/a"}, {"time_in_ms": "1000", "costs": 559.0, "plan_selection": "n/a"}, {"time_in_ms": "1500", "costs": 465.0, "plan_selection": "n/a"}, {"time_in_ms": "2000", "costs": 418.0, "plan_selection": "n/a"}, {"time_in_ms": "2500", "costs": 314.0, "plan_selection": "n/a"}, {"time_in_ms": "3000", "costs": 264.0, "plan_selection": "n/a"}, {"time_in_ms": "3500", "costs": 237.0, "plan_selection": "n/a"}, {"time_in_ms": "6000", "costs": 223.0, "plan_selection": "n/a"}, {"time_in_ms": "18500", "costs": 213.0, "plan_selection": [17, 152, 235, 328, 390, 523, 572, 636, 800, 861, 976, 1032, 1105, 1203, 1346, 1352, 1441, 1591, 1696, 1771, 1822, 1905, 2034, 2119, 2220, 2253, 2341, 2480, 2566, 2690]}]